{
    "current": {
        "1": "m",
        "2": "v",
        "3": "e",
        "4": "f",
        "5": "y",
        "6": "t",
        "7": "f",
        "8": "g",
        "9": "f",
        "10": "0"
    },
    "presets": {
        "Default": {
            "1": "m",
            "2": "v",
            "3": "e",
            "4": "f",
            "5": "y",
            "6": "t",
            "7": "f",
            "8": "g",
            "9": "f",
            "10": "0"
        },
        "first": {
            "1": "q",
            "2": "w",
            "3": "e",
            "4": "r",
            "5": "y",
            "6": "t",
            "7": "f",
            "8": "g",
            "9": "f",
            "10": "0"
        }
    },
    "2": {
        "1": "left",
        "2": "right",
        "3": "m",
        "4": "space",
        "5": "f",
        "6": "v",
        "7": "space",
        "8": "g",
        "9": "f",
        "10": "0",
        "11": "ctrl+right",
        "12": "ctrl+left"
    },
    "3": {
        "1": "left",
        "2": "right",
        "3": "m",
        "4": "space",
        "5": "f",
        "6": "v",
        "7": "space",
        "8": "g",
        "9": "i",
        "10": "0",
        "11": "ctrl+right",
        "12": "ctrl+left"
    },
    "5": {
        "1": "left",
        "2": "right",
        "3": "m",
        "4": "space",
        "5": "down",
        "6": "up",
        "7": "v",
        "8": "f",
        "9": "i",
        "10": "0",
        "11": "ctrl+right",
        "12": "ctrl+left"
    },
    "6": {
        "1": "left",
        "2": "right",
        "3": "m",
        "4": "space",
        "5": "down",
        "6": "up",
        "7": "v",
        "8": "f",
        "9": "i",
        "10": "0",
        "11": "ctrl+right",
        "12": "ctrl+left",
        "13": "s"
    },
    "1": {
        "1": "left",
        "2": "right",
        "3": "m",
        "4": "space",
        "5": "down",
        "6": "up",
        "7": "s",
        "8": "f",
        "9": "i",
        "10": "0",
        "11": "ctrl+right",
        "12": "ctrl+left",
        "13": "v"
    },
    "10": {
        "1": "left",
        "2": "right",
        "3": "m",
        "4": "space",
        "5": "down",
        "6": "up",
        "7": "s",
        "8": "f",
        "9": "z",
        "10": "0",
        "11": "ctrl+right",
        "12": "ctrl+left",
        "13": "v"
    },
    "11": {
        "1": "left",
        "2": "right",
        "3": "m",
        "4": "space",
        "5": "down",
        "6": "up",
        "7": "s",
        "8": "f",
        "9": "c",
        "10": "0",
        "11": "ctrl+right",
        "12": "ctrl+left",
        "13": "v"
    },
    "first": {
        "1": "left",
        "2": "right",
        "3": "m",
        "4": "space",
        "5": "down",
        "6": "up",
        "7": "s",
        "8": "f",
        "9": "c",
        "10": "b",
        "11": "ctrl+right",
        "12": "ctrl+left",
        "13": "v"
    },
    "9": {
        "1": "left",
        "2": "right",
        "3": "m",
        "4": "space",
        "5": "down",
        "6": "up",
        "7": "s",
        "8": "f",
        "9": "c",
        "10": "v",
        "11": "ctrl+right",
        "12": "ctrl+left",
        "13": "b"
    }
}